maskpass/__init__.py
maskpass/__main__.py
maskpass/methods/__init__.py
maskpass/methods/with_pynput.py
maskpass/methods/without_pynput.py
maskpass/methods/cross_getch/__init__.py
maskpass-0.3.7.dist-info/LICENSE
maskpass-0.3.7.dist-info/METADATA
maskpass-0.3.7.dist-info/WHEEL
maskpass-0.3.7.dist-info/top_level.txt
maskpass-0.3.7.dist-info/RECORD
