Metadata-Version: 2.1
Name: maskpass
Version: 0.3.7
Summary: getpass alternative with masking, Spyder support and additional features 
Home-page: https://github.com/FuturisticGoo/maskpass
Author: Aman Anifer
Author-email: fgoo.edu@hash.fyi
License: MIT
Keywords: password,getpass,getpass3,mask,spyder,input,pynput
Platform: UNKNOWN
Classifier: License :: OSI Approved :: MIT License
Classifier: Programming Language :: Python :: 3
Classifier: Operating System :: OS Independent
License-File: LICENSE
